simpblog.py
simpblog-0.1.1.dist-info/licenses/LICENSE
simpblog-0.1.1.dist-info/METADATA
simpblog-0.1.1.dist-info/WHEEL
simpblog-0.1.1.dist-info/entry_points.txt
simpblog-0.1.1.dist-info/top_level.txt
simpblog-0.1.1.dist-info/RECORD
