Metadata-Version: 2.4
Name: simpblog
Version: 0.1.1
Summary: Simple static site generator, for blogs and basic sites
Author-email: Alex Kennett <alex@kennett.dev>
License-Expression: MIT
Project-URL: Homepage, https://github.com/alexk49/simpblog
Requires-Python: >=3.10
License-File: LICENSE
Requires-Dist: Jinja2
Requires-Dist: markdown2
Provides-Extra: lint
Requires-Dist: ruff; extra == "lint"
Requires-Dist: mypy; extra == "lint"
Provides-Extra: dev
Requires-Dist: twine; extra == "dev"
Dynamic: license-file
